[
  {
    "kodeLab": "ARC100",
    "title": "Store, Process, and Manage Data on Google Cloud: Challenge Lab",
    "difficulty": "easy",
    "cost": 1,
    "solution": "Sorry there is no solution",
    "imageUrl": "https://placehold.co/500x500?text=Image+Lab",
    "labUrl": "https://www.cloudskillsboost.google/focuses/id_lab"
  },
  {
    "kodeLab": "ARC101",
    "title": "Monitor and Manage Google Cloud Resources: Challenge Lab",
    "difficulty": "easy",
    "cost": 1,
    "solution": "Sorry there is no solution",
    "imageUrl": "https://placehold.co/500x500?text=Image+Lab",
    "labUrl": "https://www.cloudskillsboost.google/focuses/id_lab"
  },
  {
    "kodeLab": "ARC102",
    "title": "Store, Process, and Manage Data on Google Cloud - Command Line: Challenge Lab",
    "difficulty": "easy",
    "cost": 1,
    "solution": "Sorry there is no solution",
    "imageUrl": "https://placehold.co/500x500?text=Image+Lab",
    "labUrl": "https://www.cloudskillsboost.google/focuses/id_lab"
  },
  {
    "kodeLab": "ARC103",
    "title": "Analyze BigQuery data in Connected Sheets: Challenge Lab",
    "difficulty": "easy",
    "cost": 0,
    "solution": "Sorry there is no solution",
    "imageUrl": "https://placehold.co/500x500?text=Image+Lab",
    "labUrl": "https://www.cloudskillsboost.google/focuses/id_lab"
  },
  {
    "kodeLab": "ARC104",
    "title": "Cloud Run Functions: 3 Ways: Challenge Lab",
    "difficulty": "easy",
    "cost": 1,
    "solution": "Sorry there is no solution",
    "imageUrl": "https://placehold.co/500x500?text=Image+Lab",
    "labUrl": "https://www.cloudskillsboost.google/focuses/id_lab"
  },
  {
    "kodeLab": "ARC105",
    "title": "App Building with AppSheet: Challenge Lab",
    "difficulty": "easy",
    "cost": 0,
    "solution": "Sorry there is no solution",
    "imageUrl": "https://placehold.co/500x500?text=Image+Lab",
    "labUrl": "https://www.cloudskillsboost.google/focuses/id_lab"
  },
  {
    "kodeLab": "ARC106",
    "title": "Streaming Analytics into BigQuery: Challenge Lab",
    "difficulty": "easy",
    "cost": 1,
    "solution": "Sorry there is no solution",
    "imageUrl": "https://placehold.co/500x500?text=Image+Lab",
    "labUrl": "https://www.cloudskillsboost.google/focuses/id_lab"
  },
  {
    "kodeLab": "ARC107",
    "title": "Get Started with Looker: Challenge Lab",
    "difficulty": "easy",
    "cost": 0,
    "solution": "Sorry there is no solution",
    "imageUrl": "https://placehold.co/500x500?text=Image+Lab",
    "labUrl": "https://www.cloudskillsboost.google/focuses/id_lab"
  },
  {
    "kodeLab": "ARC109",
    "title": "Getting Started with API Gateway: Challenge Lab",
    "difficulty": "easy",
    "cost": 1,
    "solution": "Sorry there is no solution",
    "imageUrl": "https://placehold.co/500x500?text=Image+Lab",
    "labUrl": "https://www.cloudskillsboost.google/focuses/id_lab"
  },
  {
    "kodeLab": "ARC110",
    "title": "Create a Streaming Data Lake on Cloud Storage: Challenge Lab",
    "difficulty": "easy",
    "cost": 1,
    "solution": "Sorry there is no solution",
    "imageUrl": "https://placehold.co/500x500?text=Image+Lab",
    "labUrl": "https://www.cloudskillsboost.google/focuses/id_lab"
  },
  {
    "kodeLab": "ARC111",
    "title": "Get Started with Cloud Storage: Challenge Lab",
    "difficulty": "easy",
    "cost": 1,
    "solution": "Sorry there is no solution",
    "imageUrl": "https://placehold.co/500x500?text=Image+Lab",
    "labUrl": "https://www.cloudskillsboost.google/focuses/id_lab"
  },
  {
    "kodeLab": "ARC112",
    "title": "App Engine: 3 Ways: Challenge Lab",
    "difficulty": "easy",
    "cost": 1,
    "solution": "Sorry there is no solution",
    "imageUrl": "https://placehold.co/500x500?text=Image+Lab",
    "labUrl": "https://www.cloudskillsboost.google/focuses/id_lab"
  },
  {
    "kodeLab": "ARC113",
    "title": "Get Started with Pub/Sub: Challenge Lab",
    "difficulty": "easy",
    "cost": 1,
    "solution": "Sorry there is no solution",
    "imageUrl": "https://placehold.co/500x500?text=Image+Lab",
    "labUrl": "https://www.cloudskillsboost.google/focuses/id_lab"
  },
  {
    "kodeLab": "ARC114",
    "title": "Analyze Speech & Language with Google APIs: Challenge Lab",
    "difficulty": "easy",
    "cost": 1,
    "solution": "Sorry there is no solution",
    "imageUrl": "https://placehold.co/500x500?text=Image+Lab",
    "labUrl": "https://www.cloudskillsboost.google/focuses/id_lab"
  },
  {
    "kodeLab": "ARC115",
    "title": "Monitoring in Google Cloud: Challenge Lab",
    "difficulty": "easy",
    "cost": 1,
    "solution": "Sorry there is no solution",
    "imageUrl": "https://placehold.co/500x500?text=Image+Lab",
    "labUrl": "https://www.cloudskillsboost.google/focuses/id_lab"
  },
  {
    "kodeLab": "ARC117",
    "title": "Get Started with Dataplex: Challenge Lab",
    "difficulty": "easy",
    "cost": 1,
    "solution": "Sorry there is no solution",
    "imageUrl": "https://placehold.co/500x500?text=Image+Lab",
    "labUrl": "https://www.cloudskillsboost.google/focuses/id_lab"
  },
  {
    "kodeLab": "ARC119",
    "title": "Create a Secure Data Lake on Cloud Storage: Challenge Lab",
    "difficulty": "easy",
    "cost": 1,
    "solution": "Sorry there is no solution",
    "imageUrl": "https://placehold.co/500x500?text=Image+Lab",
    "labUrl": "https://www.cloudskillsboost.google/focuses/id_lab"
  },
  {
    "kodeLab": "ARC120",
    "title": "The Basics of Google Cloud Compute: Challenge Lab",
    "difficulty": "easy",
    "cost": 1,
    "solution": "Sorry there is no solution",
    "imageUrl": "https://placehold.co/500x500?text=Image+Lab",
    "labUrl": "https://www.cloudskillsboost.google/focuses/id_lab"
  },
  {
    "kodeLab": "ARC123",
    "title": "Tag and Discover BigLake Data: Challenge Lab",
    "difficulty": "easy",
    "cost": 1,
    "solution": "Sorry there is no solution",
    "imageUrl": "https://placehold.co/500x500?text=Image+Lab",
    "labUrl": "https://www.cloudskillsboost.google/focuses/id_lab"
  },
  {
    "kodeLab": "ARC124",
    "title": "Networking Fundamentals on Google Cloud: Challenge Lab",
    "difficulty": "easy",
    "cost": 1,
    "solution": "Sorry there is no solution",
    "imageUrl": "https://placehold.co/500x500?text=Image+Lab",
    "labUrl": "https://www.cloudskillsboost.google/focuses/id_lab"
  },
  {
    "kodeLab": "ARC125",
    "title": "Use APIs to Work with Cloud Storage: Challenge Lab",
    "difficulty": "easy",
    "cost": 1,
    "solution": "Sorry there is no solution",
    "imageUrl": "https://placehold.co/500x500?text=Image+Lab",
    "labUrl": "https://www.cloudskillsboost.google/focuses/id_lab"
  },
  {
    "kodeLab": "ARC126",
    "title": "Develop with Apps Script and AppSheet: Challenge Lab",
    "difficulty": "easy",
    "cost": 1,
    "solution": "Sorry there is no solution",
    "imageUrl": "https://placehold.co/500x500?text=Image+Lab",
    "labUrl": "https://www.cloudskillsboost.google/focuses/id_lab"
  },
  {
    "kodeLab": "ARC129",
    "title": "Secure BigLake Data: Challenge Lab",
    "difficulty": "easy",
    "cost": 1,
    "solution": "Sorry there is no solution",
    "imageUrl": "https://placehold.co/500x500?text=Image+Lab",
    "labUrl": "https://www.cloudskillsboost.google/focuses/id_lab"
  },
  {
    "kodeLab": "ARC131",
    "title": "Using the Google Cloud Speech API: Challenge Lab",
    "difficulty": "easy",
    "cost": 1,
    "solution": "Sorry there is no solution",
    "imageUrl": "https://placehold.co/500x500?text=Image+Lab",
    "labUrl": "https://www.cloudskillsboost.google/focuses/id_lab"
  },
  {
    "kodeLab": "ARC132",
    "title": "Cloud Speech API 3 Ways: Challenge Lab",
    "difficulty": "easy",
    "cost": 1,
    "solution": "Sorry there is no solution",
    "imageUrl": "https://placehold.co/500x500?text=Image+Lab",
    "labUrl": "https://www.cloudskillsboost.google/focuses/id_lab"
  },
  {
    "kodeLab": "bb-ide-genai-002",
    "title": "Build an AI Image Generator app using Imagen on Vertex AI",
    "difficulty": "easy",
    "cost": 0,
    "solution": "Sorry there is no solution",
    "imageUrl": "https://placehold.co/500x500?text=Image+Lab",
    "labUrl": "https://www.cloudskillsboost.google/focuses/id_lab"
  },
  {
    "kodeLab": "gem-artifact-registry-container",
    "title": "Create a Container Artifact Registry and Upload Code",
    "difficulty": "easy",
    "cost": 0,
    "solution": "Sorry there is no solution",
    "imageUrl": "https://placehold.co/500x500?text=Image+Lab",
    "labUrl": "https://www.cloudskillsboost.google/focuses/id_lab"
  },
  {
    "kodeLab": "gem-artifact-registry-go",
    "title": "Create a Go Artifact Registry and Upload Code",
    "difficulty": "easy",
    "cost": 0,
    "solution": "Sorry there is no solution",
    "imageUrl": "https://placehold.co/500x500?text=Image+Lab",
    "labUrl": "https://www.cloudskillsboost.google/focuses/id_lab"
  },
  {
    "kodeLab": "gem-artifact-registry-maven",
    "title": "Create a Maven Artifact Registry and Upload Code",
    "difficulty": "easy",
    "cost": 0,
    "solution": "Sorry there is no solution",
    "imageUrl": "https://placehold.co/500x500?text=Image+Lab",
    "labUrl": "https://www.cloudskillsboost.google/focuses/id_lab"
  },
  {
    "kodeLab": "gem-artifact-registry-npm",
    "title": "Create an NPM Artifact Registry and Upload Code",
    "difficulty": "easy",
    "cost": 0,
    "solution": "Sorry there is no solution",
    "imageUrl": "https://placehold.co/500x500?text=Image+Lab",
    "labUrl": "https://www.cloudskillsboost.google/focuses/id_lab"
  },
  {
    "kodeLab": "gem-artifact-registry-python",
    "title": "Create a Python Artifact Registry and Upload Code",
    "difficulty": "easy",
    "cost": 0,
    "solution": "Sorry there is no solution",
    "imageUrl": "https://placehold.co/500x500?text=Image+Lab",
    "labUrl": "https://www.cloudskillsboost.google/focuses/id_lab"
  },
  {
    "kodeLab": "gem-cloud-run-caddy-website",
    "title": "Deploy a static site with Caddy V2 on Google Cloud Run",
    "difficulty": "easy",
    "cost": 0,
    "solution": "Sorry there is no solution",
    "imageUrl": "https://placehold.co/500x500?text=Image+Lab",
    "labUrl": "https://www.cloudskillsboost.google/focuses/id_lab"
  },
  {
    "kodeLab": "gem-cloud-run-nginx-website",
    "title": "Deploy a Static Site with Nginx on Google Cloud Run using Artifact Registry",
    "difficulty": "easy",
    "cost": 0,
    "solution": "Sorry there is no solution",
    "imageUrl": "https://placehold.co/500x500?text=Image+Lab",
    "labUrl": "https://www.cloudskillsboost.google/focuses/id_lab"
  },
  {
    "kodeLab": "gem-cloud-run-traefik-website",
    "title": "Deploy a Static Site Using Traefik and Cloud Run",
    "difficulty": "easy",
    "cost": 0,
    "solution": "Sorry there is no solution",
    "imageUrl": "https://placehold.co/500x500?text=Image+Lab",
    "labUrl": "https://www.cloudskillsboost.google/focuses/id_lab"
  },
  {
    "kodeLab": "GSP001",
    "title": "Create a Virtual Machine",
    "difficulty": "easy",
    "cost": 1,
    "solution": "Sorry there is no solution",
    "imageUrl": "https://placehold.co/500x500?text=Image+Lab",
    "labUrl": "https://www.cloudskillsboost.google/focuses/id_lab"
  },
  {
    "kodeLab": "GSP002",
    "title": "Getting Started with Cloud Shell and gcloud",
    "difficulty": "easy",
    "cost": 1,
    "solution": "Sorry there is no solution",
    "imageUrl": "https://placehold.co/500x500?text=Image+Lab",
    "labUrl": "https://www.cloudskillsboost.google/focuses/id_lab"
  },
  {
    "kodeLab": "GSP004",
    "title": "Creating a Persistent Disk",
    "difficulty": "easy",
    "cost": 1,
    "solution": "Sorry there is no solution",
    "imageUrl": "https://placehold.co/500x500?text=Image+Lab",
    "labUrl": "https://www.cloudskillsboost.google/focuses/id_lab"
  },
  {
    "kodeLab": "GSP005",
    "title": "Hello Node Kubernetes",
    "difficulty": "medium",
    "cost": 0,
    "solution": "Sorry there is no solution",
    "imageUrl": "https://placehold.co/500x500?text=Image+Lab",
    "labUrl": "https://www.cloudskillsboost.google/focuses/id_lab"
  },
  {
    "kodeLab": "GSP007",
    "title": "Set Up Network and Application Load Balancers",
    "difficulty": "easy",
    "cost": 1,
    "solution": "Sorry there is no solution",
    "imageUrl": "https://placehold.co/500x500?text=Image+Lab",
    "labUrl": "https://www.cloudskillsboost.google/focuses/id_lab"
  },
  {
    "kodeLab": "GSP008",
    "title": "Rent-a-VM to Process Earthquake Data",
    "difficulty": "easy",
    "cost": 0,
    "solution": "Sorry there is no solution",
    "imageUrl": "https://placehold.co/500x500?text=Image+Lab",
    "labUrl": "https://www.cloudskillsboost.google/focuses/id_lab"
  },
  {
    "kodeLab": "GSP015",
    "title": "Running a Containerized App on Google Kubernetes Engine",
    "difficulty": "easy",
    "cost": 0,
    "solution": "Sorry there is no solution",
    "imageUrl": "https://placehold.co/500x500?text=Image+Lab",
    "labUrl": "https://www.cloudskillsboost.google/focuses/id_lab"
  },
  {
    "kodeLab": "GSP016",
    "title": "Networking 101",
    "difficulty": "easy",
    "cost": 1,
    "solution": "Sorry there is no solution",
    "imageUrl": "https://placehold.co/500x500?text=Image+Lab",
    "labUrl": "https://www.cloudskillsboost.google/focuses/id_lab"
  },
  {
    "kodeLab": "GSP021",
    "title": "Orchestrating the Cloud with Kubernetes",
    "difficulty": "medium",
    "cost": 5,
    "solution": "Sorry there is no solution",
    "imageUrl": "https://placehold.co/500x500?text=Image+Lab",
    "labUrl": "https://www.cloudskillsboost.google/focuses/id_lab"
  },
  {
    "kodeLab": "GSP023",
    "title": "Deploying a Python Flask Web Application to App Engine Flexible",
    "difficulty": "easy",
    "cost": 0,
    "solution": "Sorry there is no solution",
    "imageUrl": "https://placehold.co/500x500?text=Image+Lab",
    "labUrl": "https://www.cloudskillsboost.google/focuses/id_lab"
  },
  {
    "kodeLab": "GSP031",
    "title": "Deploy Microsoft SQL Server to Compute Engine",
    "difficulty": "easy",
    "cost": 0,
    "solution": "Sorry there is no solution",
    "imageUrl": "https://placehold.co/500x500?text=Image+Lab",
    "labUrl": "https://www.cloudskillsboost.google/focuses/id_lab"
  },
  {
    "kodeLab": "GSP035",
    "title": "Google Workspace Admin: Getting Started",
    "difficulty": "easy",
    "cost": 0,
    "solution": "Sorry there is no solution",
    "imageUrl": "https://placehold.co/500x500?text=Image+Lab",
    "labUrl": "https://www.cloudskillsboost.google/focuses/id_lab"
  },
  {
    "kodeLab": "GSP038",
    "title": "Entity and Sentiment Analysis with the Natural Language API",
    "difficulty": "medium",
    "cost": 5,
    "solution": "Sorry there is no solution",
    "imageUrl": "https://placehold.co/500x500?text=Image+Lab",
    "labUrl": "https://www.cloudskillsboost.google/focuses/id_lab"
  },
  {
    "kodeLab": "GSP041",
    "title": "Internal Load Balancer",
    "difficulty": "easy",
    "cost": 1,
    "solution": "Sorry there is no solution",
    "imageUrl": "https://placehold.co/500x500?text=Image+Lab",
    "labUrl": "https://www.cloudskillsboost.google/focuses/id_lab"
  },
  {
    "kodeLab": "GSP048",
    "title": "Speech to Text Transcription with the Cloud Speech API",
    "difficulty": "easy",
    "cost": 1,
    "solution": "Sorry there is no solution",
    "imageUrl": "https://placehold.co/500x500?text=Image+Lab",
    "labUrl": "https://www.cloudskillsboost.google/focuses/id_lab"
  },
  {
    "kodeLab": "GSP049",
    "title": "Translate Text with the Cloud Translation API",
    "difficulty": "easy",
    "cost": 1,
    "solution": "Sorry there is no solution",
    "imageUrl": "https://placehold.co/500x500?text=Image+Lab",
    "labUrl": "https://www.cloudskillsboost.google/focuses/id_lab"
  },
  {
    "kodeLab": "GSP053",
    "title": "Managing Deployments Using Kubernetes Engine",
    "difficulty": "medium",
    "cost": 5,
    "solution": "Sorry there is no solution",
    "imageUrl": "https://placehold.co/500x500?text=Image+Lab",
    "labUrl": "https://www.cloudskillsboost.google/focuses/id_lab"
  },
  {
    "kodeLab": "GSP055",
    "title": "Introduction to Docker",
    "difficulty": "easy",
    "cost": 1,
    "solution": "Sorry there is no solution",
    "imageUrl": "https://placehold.co/500x500?text=Image+Lab",
    "labUrl": "https://www.cloudskillsboost.google/focuses/id_lab"
  },
  {
    "kodeLab": "GSP064",
    "title": "Cloud IAM: Qwik Start",
    "difficulty": "easy",
    "cost": 1,
    "solution": "Sorry there is no solution",
    "imageUrl": "https://placehold.co/500x500?text=Image+Lab",
    "labUrl": "https://www.cloudskillsboost.google/focuses/id_lab"
  },
  {
    "kodeLab": "GSP067",
    "title": "App Engine: Qwik Start - Python",
    "difficulty": "easy",
    "cost": 1,
    "solution": "Sorry there is no solution",
    "imageUrl": "https://placehold.co/500x500?text=Image+Lab",
    "labUrl": "https://www.cloudskillsboost.google/focuses/id_lab"
  },
  {
    "kodeLab": "GSP069",
    "title": "App Engine: Qwik Start - PHP",
    "difficulty": "easy",
    "cost": 1,
    "solution": "Sorry there is no solution",
    "imageUrl": "https://placehold.co/500x500?text=Image+Lab",
    "labUrl": "https://www.cloudskillsboost.google/focuses/id_lab"
  },
  {
    "kodeLab": "GSP070",
    "title": "App Engine: Qwik Start - Go",
    "difficulty": "easy",
    "cost": 1,
    "solution": "Sorry there is no solution",
    "imageUrl": "https://placehold.co/500x500?text=Image+Lab",
    "labUrl": "https://www.cloudskillsboost.google/focuses/id_lab"
  },
  {
    "kodeLab": "GSP071",
    "title": "BigQuery: Qwik Start - Command Line",
    "difficulty": "easy",
    "cost": 0,
    "solution": "Sorry there is no solution",
    "imageUrl": "https://placehold.co/500x500?text=Image+Lab",
    "labUrl": "https://www.cloudskillsboost.google/focuses/id_lab"
  },
  {
    "kodeLab": "GSP072",
    "title": "BigQuery: Qwik Start - Console",
    "difficulty": "easy",
    "cost": 0,
    "solution": "Sorry there is no solution",
    "imageUrl": "https://placehold.co/500x500?text=Image+Lab",
    "labUrl": "https://www.cloudskillsboost.google/focuses/id_lab"
  },
  {
    "kodeLab": "GSP073",
    "title": "Cloud Storage: Qwik Start - Cloud Console",
    "difficulty": "easy",
    "cost": 1,
    "solution": "Sorry there is no solution",
    "imageUrl": "https://placehold.co/500x500?text=Image+Lab",
    "labUrl": "https://www.cloudskillsboost.google/focuses/id_lab"
  },
  {
    "kodeLab": "GSP074",
    "title": "Cloud Storage: Qwik Start - CLI/SDK",
    "difficulty": "easy",
    "cost": 1,
    "solution": "Sorry there is no solution",
    "imageUrl": "https://placehold.co/500x500?text=Image+Lab",
    "labUrl": "https://www.cloudskillsboost.google/focuses/id_lab"
  },
  {
    "kodeLab": "GSP080",
    "title": "Cloud Run Functions: Qwik Start - Command Line",
    "difficulty": "easy",
    "cost": 1,
    "solution": "Sorry there is no solution",
    "imageUrl": "https://placehold.co/500x500?text=Image+Lab",
    "labUrl": "https://www.cloudskillsboost.google/focuses/id_lab"
  },
  {
    "kodeLab": "GSP081",
    "title": "Cloud Run Functions: Qwik Start - Console",
    "difficulty": "easy",
    "cost": 1,
    "solution": "Sorry there is no solution",
    "imageUrl": "https://placehold.co/500x500?text=Image+Lab",
    "labUrl": "https://www.cloudskillsboost.google/focuses/id_lab"
  },
  {
    "kodeLab": "GSP089",
    "title": "Cloud Monitoring: Qwik Start",
    "difficulty": "easy",
    "cost": 1,
    "solution": "Sorry there is no solution",
    "imageUrl": "https://placehold.co/500x500?text=Image+Lab",
    "labUrl": "https://www.cloudskillsboost.google/focuses/id_lab"
  },
  {
    "kodeLab": "GSP090",
    "title": "Monitoring Multiple Projects with Cloud Monitoring",
    "difficulty": "easy",
    "cost": 1,
    "solution": "Sorry there is no solution",
    "imageUrl": "https://placehold.co/500x500?text=Image+Lab",
    "labUrl": "https://www.cloudskillsboost.google/focuses/id_lab"
  },
  {
    "kodeLab": "GSP091",
    "title": "Creating and Alerting on Logs-based Metrics",
    "difficulty": "easy",
    "cost": 1,
    "solution": "Sorry there is no solution",
    "imageUrl": "https://placehold.co/500x500?text=Image+Lab",
    "labUrl": "https://www.cloudskillsboost.google/focuses/id_lab"
  },
  {
    "kodeLab": "GSP092",
    "title": "Monitoring and Logging for Cloud Run Functions",
    "difficulty": "easy",
    "cost": 1,
    "solution": "Sorry there is no solution",
    "imageUrl": "https://placehold.co/500x500?text=Image+Lab",
    "labUrl": "https://www.cloudskillsboost.google/focuses/id_lab"
  },
  {
    "kodeLab": "GSP093",
    "title": "Compute Engine: Qwik Start - Windows",
    "difficulty": "easy",
    "cost": 1,
    "solution": "Sorry there is no solution",
    "imageUrl": "https://placehold.co/500x500?text=Image+Lab",
    "labUrl": "https://www.cloudskillsboost.google/focuses/id_lab"
  },
  {
    "kodeLab": "GSP094",
    "title": "Pub/Sub: Qwik Start - Python",
    "difficulty": "easy",
    "cost": 1,
    "solution": "Sorry there is no solution",
    "imageUrl": "https://placehold.co/500x500?text=Image+Lab",
    "labUrl": "https://www.cloudskillsboost.google/focuses/id_lab"
  },
  {
    "kodeLab": "GSP095",
    "title": "Pub/Sub: Qwik Start - Command Line",
    "difficulty": "easy",
    "cost": 0,
    "solution": "Sorry there is no solution",
    "imageUrl": "https://placehold.co/500x500?text=Image+Lab",
    "labUrl": "https://www.cloudskillsboost.google/focuses/id_lab"
  },
  {
    "kodeLab": "GSP096",
    "title": "Pub/Sub: Qwik Start - Console",
    "difficulty": "easy",
    "cost": 0,
    "solution": "Sorry there is no solution",
    "imageUrl": "https://placehold.co/500x500?text=Image+Lab",
    "labUrl": "https://www.cloudskillsboost.google/focuses/id_lab"
  },
  {
    "kodeLab": "GSP097",
    "title": "Cloud Natural Language API: Qwik Start",
    "difficulty": "easy",
    "cost": 1,
    "solution": "Sorry there is no solution",
    "imageUrl": "https://placehold.co/500x500?text=Image+Lab",
    "labUrl": "https://www.cloudskillsboost.google/focuses/id_lab"
  },
  {
    "kodeLab": "GSP100",
    "title": "Google Kubernetes Engine: Qwik Start",
    "difficulty": "easy",
    "cost": 1,
    "solution": "Sorry there is no solution",
    "imageUrl": "https://placehold.co/500x500?text=Image+Lab",
    "labUrl": "https://www.cloudskillsboost.google/focuses/id_lab"
  },
  {
    "kodeLab": "GSP1019",
    "title": "Troubleshooting Data Models in Looker",
    "difficulty": "medium",
    "cost": 0,
    "solution": "Sorry there is no solution",
    "imageUrl": "https://placehold.co/500x500?text=Image+Lab",
    "labUrl": "https://www.cloudskillsboost.google/focuses/id_lab"
  },
  {
    "kodeLab": "GSP1020",
    "title": "Employing Best Practices for Improving the Usability of LookML Projects",
    "difficulty": "medium",
    "cost": 0,
    "solution": "Sorry there is no solution",
    "imageUrl": "https://placehold.co/500x500?text=Image+Lab",
    "labUrl": "https://www.cloudskillsboost.google/focuses/id_lab"
  },
  {
    "kodeLab": "GSP1026",
    "title": "Collect Metrics from Exporters using the Managed Service for Prometheus",
    "difficulty": "medium",
    "cost": 5,
    "solution": "Sorry there is no solution",
    "imageUrl": "https://placehold.co/500x500?text=Image+Lab",
    "labUrl": "https://www.cloudskillsboost.google/focuses/id_lab"
  },
  {
    "kodeLab": "GSP103",
    "title": "Dataproc: Qwik Start - Console",
    "difficulty": "easy",
    "cost": 0,
    "solution": "Sorry there is no solution",
    "imageUrl": "https://placehold.co/500x500?text=Image+Lab",
    "labUrl": "https://www.cloudskillsboost.google/focuses/id_lab"
  },
  {
    "kodeLab": "GSP1030",
    "title": "Publish your AppSheet App",
    "difficulty": "easy",
    "cost": 0,
    "solution": "Sorry there is no solution",
    "imageUrl": "https://placehold.co/500x500?text=Image+Lab",
    "labUrl": "https://www.cloudskillsboost.google/focuses/id_lab"
  },
  {
    "kodeLab": "GSP1036",
    "title": "Securing Virtual Machines using BeyondCorp Enterprise (BCE)",
    "difficulty": "medium",
    "cost": 0,
    "solution": "Sorry there is no solution",
    "imageUrl": "https://placehold.co/500x500?text=Image+Lab",
    "labUrl": "https://www.cloudskillsboost.google/focuses/id_lab"
  },
  {
    "kodeLab": "GSP1040",
    "title": "BigLake: Qwik Start",
    "difficulty": "easy",
    "cost": 1,
    "solution": "Sorry there is no solution",
    "imageUrl": "https://placehold.co/500x500?text=Image+Lab",
    "labUrl": "https://www.cloudskillsboost.google/focuses/id_lab"
  },
  {
    "kodeLab": "GSP1043",
    "title": "Consuming Customer Specific Datasets from Data Sharing Partners using BigQuery",
    "difficulty": "easy",
    "cost": 0,
    "solution": "Sorry there is no solution",
    "imageUrl": "https://placehold.co/500x500?text=Image+Lab",
    "labUrl": "https://www.cloudskillsboost.google/focuses/id_lab"
  },
  {
    "kodeLab": "GSP1048",
    "title": "Cloud Spanner - Database Fundamentals",
    "difficulty": "easy",
    "cost": 0,
    "solution": "Sorry there is no solution",
    "imageUrl": "https://placehold.co/500x500?text=Image+Lab",
    "labUrl": "https://www.cloudskillsboost.google/focuses/id_lab"
  },
  {
    "kodeLab": "GSP1061",
    "title": "Use Charts in Google Sheets",
    "difficulty": "medium",
    "cost": 0,
    "solution": "Sorry there is no solution",
    "imageUrl": "https://placehold.co/500x500?text=Image+Lab",
    "labUrl": "https://www.cloudskillsboost.google/focuses/id_lab"
  },
  {
    "kodeLab": "GSP1062",
    "title": "Validate Data in Google Sheets",
    "difficulty": "medium",
    "cost": 0,
    "solution": "Sorry there is no solution",
    "imageUrl": "https://placehold.co/500x500?text=Image+Lab",
    "labUrl": "https://www.cloudskillsboost.google/focuses/id_lab"
  },
  {
    "kodeLab": "GSP1063",
    "title": "Finding Data in Google Sheets",
    "difficulty": "medium",
    "cost": 0,
    "solution": "Sorry there is no solution",
    "imageUrl": "https://placehold.co/500x500?text=Image+Lab",
    "labUrl": "https://www.cloudskillsboost.google/focuses/id_lab"
  },
  {
    "kodeLab": "GSP1064",
    "title": "Use Google Forms with Google Sheets",
    "difficulty": "medium",
    "cost": 0,
    "solution": "Sorry there is no solution",
    "imageUrl": "https://placehold.co/500x500?text=Image+Lab",
    "labUrl": "https://www.cloudskillsboost.google/focuses/id_lab"
  },
  {
    "kodeLab": "GSP1065",
    "title": "Pivot Tables in Google Sheets",
    "difficulty": "medium",
    "cost": 0,
    "solution": "Sorry there is no solution",
    "imageUrl": "https://placehold.co/500x500?text=Image+Lab",
    "labUrl": "https://www.cloudskillsboost.google/focuses/id_lab"
  },
  {
    "kodeLab": "GSP1078",
    "title": "Cloud Run Canary Deployments",
    "difficulty": "medium",
    "cost": 0,
    "solution": "Sorry there is no solution",
    "imageUrl": "https://placehold.co/500x500?text=Image+Lab",
    "labUrl": "https://www.cloudskillsboost.google/focuses/id_lab"
  },
  {
    "kodeLab": "GSP1079",
    "title": "Continuous Delivery with Google Cloud Deploy",
    "difficulty": "medium",
    "cost": 0,
    "solution": "Sorry there is no solution",
    "imageUrl": "https://placehold.co/500x500?text=Image+Lab",
    "labUrl": "https://www.cloudskillsboost.google/focuses/id_lab"
  },
  {
    "kodeLab": "GSP1088",
    "title": "Log Analytics on Google Cloud",
    "difficulty": "easy",
    "cost": 0,
    "solution": "Sorry there is no solution",
    "imageUrl": "https://placehold.co/500x500?text=Image+Lab",
    "labUrl": "https://www.cloudskillsboost.google/focuses/id_lab"
  },
  {
    "kodeLab": "GSP1089",
    "title": "Cloud Run Functions: Qwik Start",
    "difficulty": "easy",
    "cost": 1,
    "solution": "Sorry there is no solution",
    "imageUrl": "https://placehold.co/500x500?text=Image+Lab",
    "labUrl": "https://www.cloudskillsboost.google/focuses/id_lab"
  },
  {
    "kodeLab": "GSP1097",
    "title": "Reconciling Account Data with Cloud Spanner Change Streams",
    "difficulty": "medium",
    "cost": 0,
    "solution": "Sorry there is no solution",
    "imageUrl": "https://placehold.co/500x500?text=Image+Lab",
    "labUrl": "https://www.cloudskillsboost.google/focuses/id_lab"
  },
  {
    "kodeLab": "GSP1098",
    "title": "Chronicle SIEM: Introduction & Single Event Rules",
    "difficulty": "easy",
    "cost": 0,
    "solution": "Sorry there is no solution",
    "imageUrl": "https://placehold.co/500x500?text=Image+Lab",
    "labUrl": "https://www.cloudskillsboost.google/focuses/id_lab"
  },
  {
    "kodeLab": "GSP1108",
    "title": "Monitor an Apache Web Server using Ops Agent",
    "difficulty": "easy",
    "cost": 1,
    "solution": "Sorry there is no solution",
    "imageUrl": "https://placehold.co/500x500?text=Image+Lab",
    "labUrl": "https://www.cloudskillsboost.google/focuses/id_lab"
  },
  {
    "kodeLab": "GSP112",
    "title": "Web Security Scanner: Qwik Start",
    "difficulty": "easy",
    "cost": 0,
    "solution": "Sorry there is no solution",
    "imageUrl": "https://placehold.co/500x500?text=Image+Lab",
    "labUrl": "https://www.cloudskillsboost.google/focuses/id_lab"
  },
  {
    "kodeLab": "GSP1143",
    "title": "Dataplex: Qwik Start - Console",
    "difficulty": "easy",
    "cost": 1,
    "solution": "Sorry there is no solution",
    "imageUrl": "https://placehold.co/500x500?text=Image+Lab",
    "labUrl": "https://www.cloudskillsboost.google/focuses/id_lab"
  },
  {
    "kodeLab": "GSP1144",
    "title": "Dataplex: Qwik Start - Command Line",
    "difficulty": "easy",
    "cost": 1,
    "solution": "Sorry there is no solution",
    "imageUrl": "https://placehold.co/500x500?text=Image+Lab",
    "labUrl": "https://www.cloudskillsboost.google/focuses/id_lab"
  },
  {
    "kodeLab": "GSP1145",
    "title": "Tagging Dataplex Assets",
    "difficulty": "easy",
    "cost": 1,
    "solution": "Sorry there is no solution",
    "imageUrl": "https://placehold.co/500x500?text=Image+Lab",
    "labUrl": "https://www.cloudskillsboost.google/focuses/id_lab"
  },
  {
    "kodeLab": "GSP1146",
    "title": "Develop No-Code Chat Apps with AppSheet",
    "difficulty": "easy",
    "cost": 0,
    "solution": "Sorry there is no solution",
    "imageUrl": "https://placehold.co/500x500?text=Image+Lab",
    "labUrl": "https://www.cloudskillsboost.google/focuses/id_lab"
  },
  {
    "kodeLab": "GSP1151",
    "title": "Generative AI with Vertex AI: Prompt Design",
    "difficulty": "easy",
    "cost": 0,
    "solution": "Sorry there is no solution",
    "imageUrl": "https://placehold.co/500x500?text=Image+Lab",
    "labUrl": "https://www.cloudskillsboost.google/focuses/id_lab"
  },
  {
    "kodeLab": "GSP1154",
    "title": "Get Started with Vertex AI Studio",
    "difficulty": "easy",
    "cost": 0,
    "solution": "Sorry there is no solution",
    "imageUrl": "https://placehold.co/500x500?text=Image+Lab",
    "labUrl": "https://www.cloudskillsboost.google/focuses/id_lab"
  },
  {
    "kodeLab": "GSP1164",
    "title": "Analyze Findings with Security Command Center",
    "difficulty": "medium",
    "cost": 0,
    "solution": "Sorry there is no solution",
    "imageUrl": "https://placehold.co/500x500?text=Image+Lab",
    "labUrl": "https://www.cloudskillsboost.google/focuses/id_lab"
  },
  {
    "kodeLab": "GSP119",
    "title": "Speech-to-Text API: Qwik Start",
    "difficulty": "easy",
    "cost": 1,
    "solution": "Sorry there is no solution",
    "imageUrl": "https://placehold.co/500x500?text=Image+Lab",
    "labUrl": "https://www.cloudskillsboost.google/focuses/id_lab"
  },
  {
    "kodeLab": "GSP1209",
    "title": "Getting Started with Google Generative AI Using the Gen AI SDK",
    "difficulty": "easy",
    "cost": 0,
    "solution": "Sorry there is no solution",
    "imageUrl": "https://placehold.co/500x500?text=Image+Lab",
    "labUrl": "https://www.cloudskillsboost.google/focuses/id_lab"
  },
  {
    "kodeLab": "GSP1227",
    "title": "Introduction to Function Calling with Gemini",
    "difficulty": "medium",
    "cost": 5,
    "solution": "Sorry there is no solution",
    "imageUrl": "https://placehold.co/500x500?text=Image+Lab",
    "labUrl": "https://www.cloudskillsboost.google/focuses/id_lab"
  },
  {
    "kodeLab": "GSP1228",
    "title": "Getting Started with the Gemini API in Vertex AI with cURL",
    "difficulty": "medium",
    "cost": 5,
    "solution": "Sorry there is no solution",
    "imageUrl": "https://placehold.co/500x500?text=Image+Lab",
    "labUrl": "https://www.cloudskillsboost.google/focuses/id_lab"
  },
  {
    "kodeLab": "GSP1229",
    "title": "Utilize the Streamlit Framework with Cloud Run and the Gemini API in Vertex AI",
    "difficulty": "medium",
    "cost": 5,
    "solution": "Sorry there is no solution",
    "imageUrl": "https://placehold.co/500x500?text=Image+Lab",
    "labUrl": "https://www.cloudskillsboost.google/focuses/id_lab"
  },
  {
    "kodeLab": "GSP125",
    "title": "Speaking with a Webpage - Streaming Speech Transcripts",
    "difficulty": "easy",
    "cost": 1,
    "solution": "Sorry there is no solution",
    "imageUrl": "https://placehold.co/500x500?text=Image+Lab",
    "labUrl": "https://www.cloudskillsboost.google/focuses/id_lab"
  },
  {
    "kodeLab": "GSP136",
    "title": "Looker Studio: Qwik Start",
    "difficulty": "easy",
    "cost": 0,
    "solution": "Sorry there is no solution",
    "imageUrl": "https://placehold.co/500x500?text=Image+Lab",
    "labUrl": "https://www.cloudskillsboost.google/focuses/id_lab"
  },
  {
    "kodeLab": "GSP156",
    "title": "Terraform Fundamentals",
    "difficulty": "easy",
    "cost": 1,
    "solution": "Sorry there is no solution",
    "imageUrl": "https://placehold.co/500x500?text=Image+Lab",
    "labUrl": "https://www.cloudskillsboost.google/focuses/id_lab"
  },
  {
    "kodeLab": "GSP192",
    "title": "Dataflow: Qwik Start - Templates",
    "difficulty": "easy",
    "cost": 1,
    "solution": "Sorry there is no solution",
    "imageUrl": "https://placehold.co/500x500?text=Image+Lab",
    "labUrl": "https://www.cloudskillsboost.google/focuses/id_lab"
  },
  {
    "kodeLab": "GSP207",
    "title": "Dataflow: Qwik Start - Python",
    "difficulty": "easy",
    "cost": 1,
    "solution": "Sorry there is no solution",
    "imageUrl": "https://placehold.co/500x500?text=Image+Lab",
    "labUrl": "https://www.cloudskillsboost.google/focuses/id_lab"
  },
  {
    "kodeLab": "GSP210",
    "title": "VPC Networking Fundamentals",
    "difficulty": "easy",
    "cost": 1,
    "solution": "Sorry there is no solution",
    "imageUrl": "https://placehold.co/500x500?text=Image+Lab",
    "labUrl": "https://www.cloudskillsboost.google/focuses/id_lab"
  },
  {
    "kodeLab": "GSP211",
    "title": "Multiple VPC Networks",
    "difficulty": "medium",
    "cost": 5,
    "solution": "Sorry there is no solution",
    "imageUrl": "https://placehold.co/500x500?text=Image+Lab",
    "labUrl": "https://www.cloudskillsboost.google/focuses/id_lab"
  },
  {
    "kodeLab": "GSP213",
    "title": "VPC Networks - Controlling Access",
    "difficulty": "medium",
    "cost": 5,
    "solution": "Sorry there is no solution",
    "imageUrl": "https://placehold.co/500x500?text=Image+Lab",
    "labUrl": "https://www.cloudskillsboost.google/focuses/id_lab"
  },
  {
    "kodeLab": "GSP215",
    "title": "Application Load Balancer with Cloud Armor",
    "difficulty": "medium",
    "cost": 5,
    "solution": "Sorry there is no solution",
    "imageUrl": "https://placehold.co/500x500?text=Image+Lab",
    "labUrl": "https://www.cloudskillsboost.google/focuses/id_lab"
  },
  {
    "kodeLab": "GSP216",
    "title": "Create an Internal Load Balancer",
    "difficulty": "medium",
    "cost": 5,
    "solution": "Sorry there is no solution",
    "imageUrl": "https://placehold.co/500x500?text=Image+Lab",
    "labUrl": "https://www.cloudskillsboost.google/focuses/id_lab"
  },
  {
    "kodeLab": "GSP222",
    "title": "It Speaks! Create Synthetic Speech Using Text-to-Speech",
    "difficulty": "easy",
    "cost": 1,
    "solution": "Sorry there is no solution",
    "imageUrl": "https://placehold.co/500x500?text=Image+Lab",
    "labUrl": "https://www.cloudskillsboost.google/focuses/id_lab"
  },
  {
    "kodeLab": "GSP235",
    "title": "Google Apps Script: Access Google Sheets, Maps & Gmail in 4 Lines of Code",
    "difficulty": "easy",
    "cost": 1,
    "solution": "Sorry there is no solution",
    "imageUrl": "https://placehold.co/500x500?text=Image+Lab",
    "labUrl": "https://www.cloudskillsboost.google/focuses/id_lab"
  },
  {
    "kodeLab": "GSP244",
    "title": "Cloud Filestore: Qwik Start",
    "difficulty": "easy",
    "cost": 0,
    "solution": "Sorry there is no solution",
    "imageUrl": "https://placehold.co/500x500?text=Image+Lab",
    "labUrl": "https://www.cloudskillsboost.google/focuses/id_lab"
  },
  {
    "kodeLab": "GSP250",
    "title": "Google Chat Bot - Apps Script",
    "difficulty": "medium",
    "cost": 5,
    "solution": "Sorry there is no solution",
    "imageUrl": "https://placehold.co/500x500?text=Image+Lab",
    "labUrl": "https://www.cloudskillsboost.google/focuses/id_lab"
  },
  {
    "kodeLab": "GSP281",
    "title": "Introduction to SQL for BigQuery and Cloud SQL",
    "difficulty": "easy",
    "cost": 1,
    "solution": "Sorry there is no solution",
    "imageUrl": "https://placehold.co/500x500?text=Image+Lab",
    "labUrl": "https://www.cloudskillsboost.google/focuses/id_lab"
  },
  {
    "kodeLab": "GSP294",
    "title": "Introduction to APIs in Google Cloud",
    "difficulty": "easy",
    "cost": 1,
    "solution": "Sorry there is no solution",
    "imageUrl": "https://placehold.co/500x500?text=Image+Lab",
    "labUrl": "https://www.cloudskillsboost.google/focuses/id_lab"
  },
  {
    "kodeLab": "GSP297",
    "title": "Google Cloud Storage - Bucket Lock",
    "difficulty": "easy",
    "cost": 1,
    "solution": "Sorry there is no solution",
    "imageUrl": "https://placehold.co/500x500?text=Image+Lab",
    "labUrl": "https://www.cloudskillsboost.google/focuses/id_lab"
  },
  {
    "kodeLab": "GSP313",
    "title": "Implement Load Balancing on Compute Engine: Challenge Lab",
    "difficulty": "easy",
    "cost": 1,
    "solution": "Sorry there is no solution",
    "imageUrl": "https://placehold.co/500x500?text=Image+Lab",
    "labUrl": "https://www.cloudskillsboost.google/focuses/id_lab"
  },
  {
    "kodeLab": "GSP314",
    "title": "Set Up a Google Cloud Network: Challenge Lab",
    "difficulty": "easy",
    "cost": 1,
    "solution": "Sorry there is no solution",
    "imageUrl": "https://placehold.co/500x500?text=Image+Lab",
    "labUrl": "https://www.cloudskillsboost.google/focuses/id_lab"
  },
  {
    "kodeLab": "GSP315",
    "title": "Set Up an App Dev Environment on Google Cloud: Challenge Lab",
    "difficulty": "easy",
    "cost": 1,
    "solution": "Sorry there is no solution",
    "imageUrl": "https://placehold.co/500x500?text=Image+Lab",
    "labUrl": "https://www.cloudskillsboost.google/focuses/id_lab"
  },
  {
    "kodeLab": "GSP318",
    "title": "Deploy Kubernetes Applications on Google Cloud: Challenge Lab",
    "difficulty": "medium",
    "cost": 5,
    "solution": "Sorry there is no solution",
    "imageUrl": "https://placehold.co/500x500?text=Image+Lab",
    "labUrl": "https://www.cloudskillsboost.google/focuses/id_lab"
  },
  {
    "kodeLab": "GSP321",
    "title": "Develop your Google Cloud Network: Challenge Lab",
    "difficulty": "medium",
    "cost": 5,
    "solution": "Sorry there is no solution",
    "imageUrl": "https://placehold.co/500x500?text=Image+Lab",
    "labUrl": "https://www.cloudskillsboost.google/focuses/id_lab"
  },
  {
    "kodeLab": "GSP322",
    "title": "Build a Secure Google Cloud Network: Challenge Lab",
    "difficulty": "medium",
    "cost": 5,
    "solution": "Sorry there is no solution",
    "imageUrl": "https://placehold.co/500x500?text=Image+Lab",
    "labUrl": "https://www.cloudskillsboost.google/focuses/id_lab"
  },
  {
    "kodeLab": "GSP338",
    "title": "Monitor and Log with Google Cloud Observability: Challenge Lab",
    "difficulty": "medium",
    "cost": 5,
    "solution": "Sorry there is no solution",
    "imageUrl": "https://placehold.co/500x500?text=Image+Lab",
    "labUrl": "https://www.cloudskillsboost.google/focuses/id_lab"
  },
  {
    "kodeLab": "GSP343",
    "title": "Optimize Costs for Google Kubernetes Engine: Challenge Lab",
    "difficulty": "medium",
    "cost": 5,
    "solution": "Sorry there is no solution",
    "imageUrl": "https://placehold.co/500x500?text=Image+Lab",
    "labUrl": "https://www.cloudskillsboost.google/focuses/id_lab"
  },
  {
    "kodeLab": "GSP344",
    "title": "Develop Serverless Apps with Firebase: Challenge Lab",
    "difficulty": "medium",
    "cost": 5,
    "solution": "Sorry there is no solution",
    "imageUrl": "https://placehold.co/500x500?text=Image+Lab",
    "labUrl": "https://www.cloudskillsboost.google/focuses/id_lab"
  },
  {
    "kodeLab": "GSP345",
    "title": "Build Infrastructure with Terraform on Google Cloud: Challenge Lab",
    "difficulty": "medium",
    "cost": 5,
    "solution": "Sorry there is no solution",
    "imageUrl": "https://placehold.co/500x500?text=Image+Lab",
    "labUrl": "https://www.cloudskillsboost.google/focuses/id_lab"
  },
  {
    "kodeLab": "GSP346",
    "title": "Prepare Data for Looker Dashboards and Reports: Challenge Lab",
    "difficulty": "easy",
    "cost": 0,
    "solution": "Sorry there is no solution",
    "imageUrl": "https://placehold.co/500x500?text=Image+Lab",
    "labUrl": "https://www.cloudskillsboost.google/focuses/id_lab"
  },
  {
    "kodeLab": "GSP361",
    "title": "Build LookML Objects in Looker: Challenge Lab",
    "difficulty": "medium",
    "cost": 0,
    "solution": "Sorry there is no solution",
    "imageUrl": "https://placehold.co/500x500?text=Image+Lab",
    "labUrl": "https://www.cloudskillsboost.google/focuses/id_lab"
  },
  {
    "kodeLab": "GSP365",
    "title": "Manage Data Models in Looker: Challenge Lab",
    "difficulty": "medium",
    "cost": 0,
    "solution": "Sorry there is no solution",
    "imageUrl": "https://placehold.co/500x500?text=Image+Lab",
    "labUrl": "https://www.cloudskillsboost.google/focuses/id_lab"
  },
  {
    "kodeLab": "GSP376",
    "title": "Get Started with Google Workspace Tools: Challenge Lab",
    "difficulty": "easy",
    "cost": 0,
    "solution": "Sorry there is no solution",
    "imageUrl": "https://placehold.co/500x500?text=Image+Lab",
    "labUrl": "https://www.cloudskillsboost.google/focuses/id_lab"
  },
  {
    "kodeLab": "GSP379",
    "title": "Use Functions, Formulas, and Charts in Google Sheets: Challenge Lab",
    "difficulty": "medium",
    "cost": 0,
    "solution": "Sorry there is no solution",
    "imageUrl": "https://placehold.co/500x500?text=Image+Lab",
    "labUrl": "https://www.cloudskillsboost.google/focuses/id_lab"
  },
  {
    "kodeLab": "GSP401",
    "title": "Cloud Scheduler: Qwik Start",
    "difficulty": "easy",
    "cost": 1,
    "solution": "Sorry there is no solution",
    "imageUrl": "https://placehold.co/500x500?text=Image+Lab",
    "labUrl": "https://www.cloudskillsboost.google/focuses/id_lab"
  },
  {
    "kodeLab": "GSP407",
    "title": "Explore an Ecommerce Dataset with SQL in BigQuery",
    "difficulty": "easy",
    "cost": 0,
    "solution": "Sorry there is no solution",
    "imageUrl": "https://placehold.co/500x500?text=Image+Lab",
    "labUrl": "https://www.cloudskillsboost.google/focuses/id_lab"
  },
  {
    "kodeLab": "GSP408",
    "title": "Troubleshooting Common SQL Errors with BigQuery",
    "difficulty": "easy",
    "cost": 0,
    "solution": "Sorry there is no solution",
    "imageUrl": "https://placehold.co/500x500?text=Image+Lab",
    "labUrl": "https://www.cloudskillsboost.google/focuses/id_lab"
  },
  {
    "kodeLab": "GSP409",
    "title": "Explore and Create Reports with Looker Studio",
    "difficulty": "easy",
    "cost": 0,
    "solution": "Sorry there is no solution",
    "imageUrl": "https://placehold.co/500x500?text=Image+Lab",
    "labUrl": "https://www.cloudskillsboost.google/focuses/id_lab"
  },
  {
    "kodeLab": "GSP421",
    "title": "APIs Explorer: Cloud Storage",
    "difficulty": "easy",
    "cost": 1,
    "solution": "Sorry there is no solution",
    "imageUrl": "https://placehold.co/500x500?text=Image+Lab",
    "labUrl": "https://www.cloudskillsboost.google/focuses/id_lab"
  },
  {
    "kodeLab": "GSP465",
    "title": "Gmail: Getting Started",
    "difficulty": "easy",
    "cost": 0,
    "solution": "Sorry there is no solution",
    "imageUrl": "https://placehold.co/500x500?text=Image+Lab",
    "labUrl": "https://www.cloudskillsboost.google/focuses/id_lab"
  },
  {
    "kodeLab": "GSP466",
    "title": "Google Calendar: Getting Started",
    "difficulty": "easy",
    "cost": 0,
    "solution": "Sorry there is no solution",
    "imageUrl": "https://placehold.co/500x500?text=Image+Lab",
    "labUrl": "https://www.cloudskillsboost.google/focuses/id_lab"
  },
  {
    "kodeLab": "GSP467",
    "title": "Google Meet: Getting Started",
    "difficulty": "easy",
    "cost": 0,
    "solution": "Sorry there is no solution",
    "imageUrl": "https://placehold.co/500x500?text=Image+Lab",
    "labUrl": "https://www.cloudskillsboost.google/focuses/id_lab"
  },
  {
    "kodeLab": "GSP468",
    "title": "Google Drive: Getting Started",
    "difficulty": "easy",
    "cost": 0,
    "solution": "Sorry there is no solution",
    "imageUrl": "https://placehold.co/500x500?text=Image+Lab",
    "labUrl": "https://www.cloudskillsboost.google/focuses/id_lab"
  },
  {
    "kodeLab": "GSP469",
    "title": "Google Sheets: Getting Started",
    "difficulty": "easy",
    "cost": 0,
    "solution": "Sorry there is no solution",
    "imageUrl": "https://placehold.co/500x500?text=Image+Lab",
    "labUrl": "https://www.cloudskillsboost.google/focuses/id_lab"
  },
  {
    "kodeLab": "GSP510",
    "title": "Manage Kubernetes in Google Cloud: Challenge Lab",
    "difficulty": "medium",
    "cost": 5,
    "solution": "Sorry there is no solution",
    "imageUrl": "https://placehold.co/500x500?text=Image+Lab",
    "labUrl": "https://www.cloudskillsboost.google/focuses/id_lab"
  },
  {
    "kodeLab": "GSP517",
    "title": "Develop GenAI Apps with Gemini and Streamlit: Challenge Lab",
    "difficulty": "medium",
    "cost": 5,
    "solution": "Sorry there is no solution",
    "imageUrl": "https://placehold.co/500x500?text=Image+Lab",
    "labUrl": "https://www.cloudskillsboost.google/focuses/id_lab"
  },
  {
    "kodeLab": "GSP519",
    "title": "Prompt Design in Vertex AI: Challenge Lab",
    "difficulty": "easy",
    "cost": 0,
    "solution": "Sorry there is no solution",
    "imageUrl": "https://placehold.co/500x500?text=Image+Lab",
    "labUrl": "https://www.cloudskillsboost.google/focuses/id_lab"
  },
  {
    "kodeLab": "GSP617",
    "title": "Using BigQuery and Cloud Logging to Analyze BigQuery Usage",
    "difficulty": "easy",
    "cost": 1,
    "solution": "Sorry there is no solution",
    "imageUrl": "https://placehold.co/500x500?text=Image+Lab",
    "labUrl": "https://www.cloudskillsboost.google/focuses/id_lab"
  },
  {
    "kodeLab": "GSP642",
    "title": "Importing Data to a Firestore Database",
    "difficulty": "easy",
    "cost": 1,
    "solution": "Sorry there is no solution",
    "imageUrl": "https://placehold.co/500x500?text=Image+Lab",
    "labUrl": "https://www.cloudskillsboost.google/focuses/id_lab"
  },
  {
    "kodeLab": "GSP643",
    "title": "Build a Serverless Web App with Firebase",
    "difficulty": "medium",
    "cost": 5,
    "solution": "Sorry there is no solution",
    "imageUrl": "https://placehold.co/500x500?text=Image+Lab",
    "labUrl": "https://www.cloudskillsboost.google/focuses/id_lab"
  },
  {
    "kodeLab": "GSP644",
    "title": "Build a Serverless App with Cloud Run that Creates PDF Files",
    "difficulty": "medium",
    "cost": 0,
    "solution": "Sorry there is no solution",
    "imageUrl": "https://placehold.co/500x500?text=Image+Lab",
    "labUrl": "https://www.cloudskillsboost.google/focuses/id_lab"
  },
  {
    "kodeLab": "GSP647",
    "title": "Configuring IAM Permissions with gcloud",
    "difficulty": "easy",
    "cost": 1,
    "solution": "Sorry there is no solution",
    "imageUrl": "https://placehold.co/500x500?text=Image+Lab",
    "labUrl": "https://www.cloudskillsboost.google/focuses/id_lab"
  },
  {
    "kodeLab": "GSP650",
    "title": "Build a Resilient, Asynchronous System with Cloud Run and Pub/Sub",
    "difficulty": "medium",
    "cost": 0,
    "solution": "Sorry there is no solution",
    "imageUrl": "https://placehold.co/500x500?text=Image+Lab",
    "labUrl": "https://www.cloudskillsboost.google/focuses/id_lab"
  },
  {
    "kodeLab": "GSP662",
    "title": "Hosting a Web App on Google Cloud Using Compute Engine",
    "difficulty": "easy",
    "cost": 1,
    "solution": "Sorry there is no solution",
    "imageUrl": "https://placehold.co/500x500?text=Image+Lab",
    "labUrl": "https://www.cloudskillsboost.google/focuses/id_lab"
  },
  {
    "kodeLab": "GSP676",
    "title": "Google Workspace Admin: Provisioning",
    "difficulty": "easy",
    "cost": 0,
    "solution": "Sorry there is no solution",
    "imageUrl": "https://placehold.co/500x500?text=Image+Lab",
    "labUrl": "https://www.cloudskillsboost.google/focuses/id_lab"
  },
  {
    "kodeLab": "GSP687",
    "title": "Google Workspace Admin: Managing Google Meet",
    "difficulty": "easy",
    "cost": 0,
    "solution": "Sorry there is no solution",
    "imageUrl": "https://placehold.co/500x500?text=Image+Lab",
    "labUrl": "https://www.cloudskillsboost.google/focuses/id_lab"
  },
  {
    "kodeLab": "GSP718",
    "title": "Looker Data Explorer - Qwik Start",
    "difficulty": "easy",
    "cost": 0,
    "solution": "Sorry there is no solution",
    "imageUrl": "https://placehold.co/500x500?text=Image+Lab",
    "labUrl": "https://www.cloudskillsboost.google/focuses/id_lab"
  },
  {
    "kodeLab": "GSP729",
    "title": "Data Catalog: Qwik Start",
    "difficulty": "easy",
    "cost": 1,
    "solution": "Sorry there is no solution",
    "imageUrl": "https://placehold.co/500x500?text=Image+Lab",
    "labUrl": "https://www.cloudskillsboost.google/focuses/id_lab"
  },
  {
    "kodeLab": "GSP736",
    "title": "Debugging Apps on Google Kubernetes Engine",
    "difficulty": "medium",
    "cost": 5,
    "solution": "Sorry there is no solution",
    "imageUrl": "https://placehold.co/500x500?text=Image+Lab",
    "labUrl": "https://www.cloudskillsboost.google/focuses/id_lab"
  },
  {
    "kodeLab": "GSP747",
    "title": "Deploy a Hugo Website with Cloud Build and Firebase Pipeline",
    "difficulty": "medium",
    "cost": 5,
    "solution": "Sorry there is no solution",
    "imageUrl": "https://placehold.co/500x500?text=Image+Lab",
    "labUrl": "https://www.cloudskillsboost.google/focuses/id_lab"
  },
  {
    "kodeLab": "GSP750",
    "title": "Infrastructure as Code with Terraform",
    "difficulty": "medium",
    "cost": 5,
    "solution": "Sorry there is no solution",
    "imageUrl": "https://placehold.co/500x500?text=Image+Lab",
    "labUrl": "https://www.cloudskillsboost.google/focuses/id_lab"
  },
  {
    "kodeLab": "GSP751",
    "title": "Interact with Terraform Modules",
    "difficulty": "medium",
    "cost": 5,
    "solution": "Sorry there is no solution",
    "imageUrl": "https://placehold.co/500x500?text=Image+Lab",
    "labUrl": "https://www.cloudskillsboost.google/focuses/id_lab"
  },
  {
    "kodeLab": "GSP752",
    "title": "Managing Terraform State",
    "difficulty": "medium",
    "cost": 5,
    "solution": "Sorry there is no solution",
    "imageUrl": "https://placehold.co/500x500?text=Image+Lab",
    "labUrl": "https://www.cloudskillsboost.google/focuses/id_lab"
  },
  {
    "kodeLab": "GSP766",
    "title": "Managing a GKE Multi-tenant Cluster with Namespaces",
    "difficulty": "medium",
    "cost": 5,
    "solution": "Sorry there is no solution",
    "imageUrl": "https://placehold.co/500x500?text=Image+Lab",
    "labUrl": "https://www.cloudskillsboost.google/focuses/id_lab"
  },
  {
    "kodeLab": "GSP767",
    "title": "Exploring Cost-optimization for GKE Virtual Machines",
    "difficulty": "medium",
    "cost": 5,
    "solution": "Sorry there is no solution",
    "imageUrl": "https://placehold.co/500x500?text=Image+Lab",
    "labUrl": "https://www.cloudskillsboost.google/focuses/id_lab"
  },
  {
    "kodeLab": "GSP768",
    "title": "Understanding and Combining GKE Autoscaling Strategies",
    "difficulty": "medium",
    "cost": 5,
    "solution": "Sorry there is no solution",
    "imageUrl": "https://placehold.co/500x500?text=Image+Lab",
    "labUrl": "https://www.cloudskillsboost.google/focuses/id_lab"
  },
  {
    "kodeLab": "GSP769",
    "title": "GKE Workload Optimization",
    "difficulty": "medium",
    "cost": 5,
    "solution": "Sorry there is no solution",
    "imageUrl": "https://placehold.co/500x500?text=Image+Lab",
    "labUrl": "https://www.cloudskillsboost.google/focuses/id_lab"
  },
  {
    "kodeLab": "GSP787",
    "title": "Derive Insights from BigQuery Data: Challenge Lab",
    "difficulty": "medium",
    "cost": 5,
    "solution": "Sorry there is no solution",
    "imageUrl": "https://placehold.co/500x500?text=Image+Lab",
    "labUrl": "https://www.cloudskillsboost.google/focuses/id_lab"
  },
  {
    "kodeLab": "GSP850",
    "title": "BigQuery Soccer Data Analytical Insight",
    "difficulty": "medium",
    "cost": 0,
    "solution": "Sorry there is no solution",
    "imageUrl": "https://placehold.co/500x500?text=Image+Lab",
    "labUrl": "https://www.cloudskillsboost.google/focuses/id_lab"
  },
  {
    "kodeLab": "GSP855",
    "title": "Filtering and Sorting Data in Looker",
    "difficulty": "easy",
    "cost": 0,
    "solution": "Sorry there is no solution",
    "imageUrl": "https://placehold.co/500x500?text=Image+Lab",
    "labUrl": "https://www.cloudskillsboost.google/focuses/id_lab"
  },
  {
    "kodeLab": "GSP856",
    "title": "Merging Results from Different Explores in Looker",
    "difficulty": "easy",
    "cost": 0,
    "solution": "Sorry there is no solution",
    "imageUrl": "https://placehold.co/500x500?text=Image+Lab",
    "labUrl": "https://www.cloudskillsboost.google/focuses/id_lab"
  },
  {
    "kodeLab": "GSP857",
    "title": "Looker Functions and Operators",
    "difficulty": "easy",
    "cost": 0,
    "solution": "Sorry there is no solution",
    "imageUrl": "https://placehold.co/500x500?text=Image+Lab",
    "labUrl": "https://www.cloudskillsboost.google/focuses/id_lab"
  },
  {
    "kodeLab": "GSP858",
    "title": "Creating Derived Tables Using LookML",
    "difficulty": "easy",
    "cost": 0,
    "solution": "Sorry there is no solution",
    "imageUrl": "https://placehold.co/500x500?text=Image+Lab",
    "labUrl": "https://www.cloudskillsboost.google/focuses/id_lab"
  },
  {
    "kodeLab": "GSP864",
    "title": "Redacting Critical Data with Sensitive Data Protection",
    "difficulty": "easy",
    "cost": 0,
    "solution": "Sorry there is no solution",
    "imageUrl": "https://placehold.co/500x500?text=Image+Lab",
    "labUrl": "https://www.cloudskillsboost.google/focuses/id_lab"
  },
  {
    "kodeLab": "GSP870",
    "title": "Connected Sheets: Qwik Start",
    "difficulty": "easy",
    "cost": 0,
    "solution": "Sorry there is no solution",
    "imageUrl": "https://placehold.co/500x500?text=Image+Lab",
    "labUrl": "https://www.cloudskillsboost.google/focuses/id_lab"
  },
  {
    "kodeLab": "GSP872",
    "title": "API Gateway: Qwik Start",
    "difficulty": "easy",
    "cost": 1,
    "solution": "Sorry there is no solution",
    "imageUrl": "https://placehold.co/500x500?text=Image+Lab",
    "labUrl": "https://www.cloudskillsboost.google/focuses/id_lab"
  },
  {
    "kodeLab": "GSP883",
    "title": "Google AppSheet: Getting Started",
    "difficulty": "easy",
    "cost": 0,
    "solution": "Sorry there is no solution",
    "imageUrl": "https://placehold.co/500x500?text=Image+Lab",
    "labUrl": "https://www.cloudskillsboost.google/focuses/id_lab"
  },
  {
    "kodeLab": "GSP890",
    "title": "Creating Measures and Dimensions Using LookML",
    "difficulty": "easy",
    "cost": 0,
    "solution": "Sorry there is no solution",
    "imageUrl": "https://placehold.co/500x500?text=Image+Lab",
    "labUrl": "https://www.cloudskillsboost.google/focuses/id_lab"
  },
  {
    "kodeLab": "GSP891",
    "title": "Looker Developer: Qwik Start",
    "difficulty": "easy",
    "cost": 0,
    "solution": "Sorry there is no solution",
    "imageUrl": "https://placehold.co/500x500?text=Image+Lab",
    "labUrl": "https://www.cloudskillsboost.google/focuses/id_lab"
  },
  {
    "kodeLab": "GSP892",
    "title": "Filtering Explores with LookML",
    "difficulty": "easy",
    "cost": 0,
    "solution": "Sorry there is no solution",
    "imageUrl": "https://placehold.co/500x500?text=Image+Lab",
    "labUrl": "https://www.cloudskillsboost.google/focuses/id_lab"
  },
  {
    "kodeLab": "GSP893",
    "title": "Caching and Datagroups with LookML",
    "difficulty": "medium",
    "cost": 0,
    "solution": "Sorry there is no solution",
    "imageUrl": "https://placehold.co/500x500?text=Image+Lab",
    "labUrl": "https://www.cloudskillsboost.google/focuses/id_lab"
  },
  {
    "kodeLab": "GSP903",
    "title": "Stream Processing with Cloud Pub/Sub and Dataflow: Qwik Start",
    "difficulty": "easy",
    "cost": 1,
    "solution": "Sorry there is no solution",
    "imageUrl": "https://placehold.co/500x500?text=Image+Lab",
    "labUrl": "https://www.cloudskillsboost.google/focuses/id_lab"
  },
  {
    "kodeLab": "GSP910",
    "title": "Connect and Configure Data for your AppSheet App",
    "difficulty": "easy",
    "cost": 0,
    "solution": "Sorry there is no solution",
    "imageUrl": "https://placehold.co/500x500?text=Image+Lab",
    "labUrl": "https://www.cloudskillsboost.google/focuses/id_lab"
  },
  {
    "kodeLab": "GSP918",
    "title": "Migrate to Cloud SQL for PostgreSQL using Database Migration Service",
    "difficulty": "easy",
    "cost": 1,
    "solution": "Sorry there is no solution",
    "imageUrl": "https://placehold.co/500x500?text=Image+Lab",
    "labUrl": "https://www.cloudskillsboost.google/focuses/id_lab"
  },
  {
    "kodeLab": "GSP919",
    "title": "Connect an App to a Cloud SQL for PostgreSQL Instance",
    "difficulty": "easy",
    "cost": 0,
    "solution": "Sorry there is no solution",
    "imageUrl": "https://placehold.co/500x500?text=Image+Lab",
    "labUrl": "https://www.cloudskillsboost.google/focuses/id_lab"
  },
  {
    "kodeLab": "GSP924",
    "title": "Create and Test a Document AI Processor",
    "difficulty": "easy",
    "cost": 0,
    "solution": "Sorry there is no solution",
    "imageUrl": "https://placehold.co/500x500?text=Image+Lab",
    "labUrl": "https://www.cloudskillsboost.google/focuses/id_lab"
  },
  {
    "kodeLab": "GSP932",
    "title": "Creating dynamic SQL derived tables with LookML and Liquid",
    "difficulty": "medium",
    "cost": 0,
    "solution": "Sorry there is no solution",
    "imageUrl": "https://placehold.co/500x500?text=Image+Lab",
    "labUrl": "https://www.cloudskillsboost.google/focuses/id_lab"
  },
  {
    "kodeLab": "GSP935",
    "title": "Answering Complex Questions Using Native Derived Tables with LookML",
    "difficulty": "medium",
    "cost": 0,
    "solution": "Sorry there is no solution",
    "imageUrl": "https://placehold.co/500x500?text=Image+Lab",
    "labUrl": "https://www.cloudskillsboost.google/focuses/id_lab"
  },
  {
    "kodeLab": "GSP936",
    "title": "Modularizing LookML Code with Extends",
    "difficulty": "medium",
    "cost": 0,
    "solution": "Sorry there is no solution",
    "imageUrl": "https://placehold.co/500x500?text=Image+Lab",
    "labUrl": "https://www.cloudskillsboost.google/focuses/id_lab"
  },
  {
    "kodeLab": "GSP948",
    "title": "Google Workspace Admin: Super Admin Account Recovery",
    "difficulty": "easy",
    "cost": 0,
    "solution": "Sorry there is no solution",
    "imageUrl": "https://placehold.co/500x500?text=Image+Lab",
    "labUrl": "https://www.cloudskillsboost.google/focuses/id_lab"
  },
  {
    "kodeLab": "GSP957",
    "title": "GKE Autopilot: Qwik Start",
    "difficulty": "easy",
    "cost": 0,
    "solution": "Sorry there is no solution",
    "imageUrl": "https://placehold.co/500x500?text=Image+Lab",
    "labUrl": "https://www.cloudskillsboost.google/focuses/id_lab"
  },
  {
    "kodeLab": "GSP975",
    "title": "Rate Limiting with Cloud Armor",
    "difficulty": "easy",
    "cost": 0,
    "solution": "Sorry there is no solution",
    "imageUrl": "https://placehold.co/500x500?text=Image+Lab",
    "labUrl": "https://www.cloudskillsboost.google/focuses/id_lab"
  },
  {
    "kodeLab": "GSP985",
    "title": "Optimizing Performance of LookML Queries",
    "difficulty": "medium",
    "cost": 0,
    "solution": "Sorry there is no solution",
    "imageUrl": "https://placehold.co/500x500?text=Image+Lab",
    "labUrl": "https://www.cloudskillsboost.google/focuses/id_lab"
  },
  {
    "kodeLab": "GSP374",
    "title": "Perform Predictive Data Analysis in BigQuery: Challenge Lab",
    "difficulty": "hard",
    "cost": 7,
    "solution": "Sorry there is no solution",
    "imageUrl": "https://placehold.co/500x500?text=Image+Lab",
    "labUrl": "https://www.cloudskillsboost.google/focuses/id_lab"
  },
  {
    "kodeLab": "GSP515",
    "title": "Explore Generative AI with the Gemini API in Vertex AI: Challenge Lab",
    "difficulty": "medium",
    "cost": 5,
    "solution": "Sorry there is no solution",
    "imageUrl": "https://placehold.co/500x500?text=Image+Lab",
    "labUrl": "https://www.cloudskillsboost.google/focuses/id_lab"
  }
]
